modelldcatnotordf/__init__.py
modelldcatnotordf/conceptscheme.py
modelldcatnotordf/document.py
modelldcatnotordf/licensedocument.py
modelldcatnotordf/modelldcatno.py
modelldcatnotordf-1.1.1.dist-info/LICENSE
modelldcatnotordf-1.1.1.dist-info/WHEEL
modelldcatnotordf-1.1.1.dist-info/METADATA
modelldcatnotordf-1.1.1.dist-info/RECORD
