Metadata-Version: 2.1
Name: modelldcatnotordf
Version: 1.1.1
Summary: A library for mapping a modelldcatno model to rdf
Home-page: https://github.com/Informasjonsforvaltning/modelldcatnotordf
License: Apache-2.0
Author: Stig B. Dørmænen
Author-email: stigbd@gmail.com
Requires-Python: >=3.7,<4.0
Classifier: License :: OSI Approved :: Apache Software License
Classifier: Operating System :: OS Independent
Classifier: Programming Language :: Python :: 3
Classifier: Programming Language :: Python :: 3.10
Classifier: Programming Language :: Python :: 3.7
Classifier: Programming Language :: Python :: 3.8
Classifier: Programming Language :: Python :: 3.9
Requires-Dist: concepttordf (>=1.0.0,<2.0.0)
Requires-Dist: datacatalogtordf (>=1.2.0,<2.0.0)
Requires-Dist: importlib_metadata (>=1.5.0,<2.0.0); python_version < "3.9"
Requires-Dist: pytest-mock (>=3.5.1,<4.0.0)
Requires-Dist: rdflib (>=6.0.1,<7.0.0)
Requires-Dist: skolemizer (>=1.1.0,<2.0.0)
Requires-Dist: validators (>=0.18.2,<0.19.0)
Project-URL: Documentation, https://modelldcatnotordf.readthedocs.io
Project-URL: Repository, https://github.com/Informasjonsforvaltning/modelldcatnotordf
